{
  "main": {
    "id": "4565958039c23a70",
    "type": "split",
    "children": [
      {
        "id": "0db5c945c71a3e8b",
        "type": "tabs",
        "children": [
          {
            "id": "7ce3e046f51ab190",
            "type": "leaf",
            "state": {
              "type": "excalidraw",
              "state": {
                "file": "Ingeniería Electrónica/Comunicaciones/Comu II/Clase 1 - Gram Schmidt.md"
              },
              "icon": "excalidraw-icon",
              "title": "Clase 1 - Gram Schmidt"
            }
          },
          {
            "id": "c21ada8cf998c9b7",
            "type": "leaf",
            "state": {
              "type": "excalidraw",
              "state": {
                "file": "Ingeniería Electrónica/Comunicaciones/Comu II/Clase 2 - Continuación GS y Códigos de Línea.md"
              },
              "icon": "excalidraw-icon",
              "title": "Clase 2 - Continuación GS y Códigos de Línea"
            }
          }
        ],
        "currentTab": 1
      }
    ],
    "direction": "vertical"
  },
  "left": {
    "id": "9932c5c9c08c0f8a",
    "type": "split",
    "children": [
      {
        "id": "c00dca864c5f7b1e",
        "type": "tabs",
        "children": [
          {
            "id": "6a6893f65b1ee540",
            "type": "leaf",
            "state": {
              "type": "file-explorer",
              "state": {
                "sortOrder": "alphabetical"
              },
              "icon": "lucide-folder-closed",
              "title": "Files"
            }
          },
          {
            "id": "567c2eb7da2dcc33",
            "type": "leaf",
            "state": {
              "type": "search",
              "state": {
                "query": "",
                "matchingCase": false,
                "explainSearch": false,
                "collapseAll": false,
                "extraContext": false,
                "sortOrder": "alphabetical"
              },
              "icon": "lucide-search",
              "title": "Search"
            }
          },
          {
            "id": "9f01971d50307f03",
            "type": "leaf",
            "state": {
              "type": "bookmarks",
              "state": {},
              "icon": "lucide-bookmark",
              "title": "Bookmarks"
            }
          },
          {
            "id": "6698c51066789092",
            "type": "leaf",
            "state": {
              "type": "mk-path-view",
              "state": {},
              "icon": "layout-grid",
              "title": "Spaces"
            }
          }
        ]
      }
    ],
    "direction": "horizontal",
    "width": 200,
    "collapsed": true
  },
  "right": {
    "id": "bcb93a0b9425d007",
    "type": "split",
    "children": [
      {
        "id": "fe81b86382dc2f38",
        "type": "tabs",
        "children": [
          {
            "id": "ec6bdca2a68d243f",
            "type": "leaf",
            "state": {
              "type": "backlink",
              "state": {
                "file": "Mate/Matemática 6/Matemática 6.md",
                "collapseAll": false,
                "extraContext": false,
                "sortOrder": "alphabetical",
                "showSearch": false,
                "searchQuery": "",
                "backlinkCollapsed": false,
                "unlinkedCollapsed": true
              },
              "icon": "links-coming-in",
              "title": "Backlinks for Matemática 6"
            }
          },
          {
            "id": "a6a2362d14cfc44b",
            "type": "leaf",
            "state": {
              "type": "outgoing-link",
              "state": {
                "file": "Mate/Matemática 6/Matemática 6.md",
                "linksCollapsed": false,
                "unlinkedCollapsed": true
              },
              "icon": "links-going-out",
              "title": "Outgoing links from Matemática 6"
            }
          },
          {
            "id": "300392a53059716c",
            "type": "leaf",
            "state": {
              "type": "tag",
              "state": {
                "sortOrder": "frequency",
                "useHierarchy": true
              },
              "icon": "lucide-tags",
              "title": "Tags"
            }
          },
          {
            "id": "bf99575b18147f9e",
            "type": "leaf",
            "state": {
              "type": "outline",
              "state": {
                "file": "Mate/Matemática 6/Matemática 6.md"
              },
              "icon": "lucide-list",
              "title": "Outline of Matemática 6"
            }
          },
          {
            "id": "0b5e36c795e63b06",
            "type": "leaf",
            "state": {
              "type": "git-view",
              "state": {},
              "icon": "git-pull-request",
              "title": "Source Control"
            }
          }
        ],
        "currentTab": 4
      }
    ],
    "direction": "horizontal",
    "width": 368.5,
    "collapsed": true
  },
  "left-ribbon": {
    "hiddenItems": {
      "switcher:Open quick switcher": false,
      "graph:Open graph view": false,
      "canvas:Create new canvas": false,
      "daily-notes:Open today's daily note": false,
      "templates:Insert template": false,
      "command-palette:Open command palette": false,
      "obsidian-excalidraw-plugin:Create new drawing": false,
      "obsidian-git:Open Git source control": false
    }
  },
  "active": "c21ada8cf998c9b7",
  "lastOpenFiles": [
    "Attachments/image_313.png",
    "Attachments/image_312.png",
    "Attachments/image_311.png",
    "Attachments/image_310.png",
    "Attachments/image_309.png",
    "Attachments/image_308.png",
    "Attachments/image_307.png",
    "Attachments/image_306.png",
    "Attachments/image_305.png",
    "Attachments/image_304.png",
    "Attachments/image_303.png",
    "Ingeniería Electrónica/Comunicaciones/Comu II/Clase 2 - Continuación GS y Códigos de Línea.md",
    "Ingeniería Electrónica/Electrónica/Electro 4/Cálculos Informe I.md",
    "Ingeniería Electrónica/Electrónica/Electro 4",
    "Ingeniería Electrónica/Electrónica",
    "Ingeniería Electrónica/Comunicaciones/Comu II/Untitled.md",
    "Notas.md",
    "Ingeniería Electrónica/Comunicaciones/Comu II/Clase 1 - Gram Schmidt.md",
    "Ingeniería Electrónica/Ingeniería Electrónica.md",
    "Ingeniería Electrónica/Mate/Mate.md",
    "1-Campos conservativos e integrales de línea y superficie.md",
    "Ingeniería Electrónica/Comunicaciones/Comu I/1-Intro.md",
    "Ingeniería Electrónica",
    "Ingeniería Electrónica/Comunicaciones/Comu II/Comu II.md",
    "Ingeniería Electrónica/Comunicaciones/Comu II",
    "Comunicaciones/Untitled.md",
    "Ingeniería Electrónica/Comunicaciones/Comu I/Comu I.md",
    "Ingeniería Electrónica/Comunicaciones/Comu I",
    "Ingeniería Electrónica/Mecatrónica/12-Planificación de Trayectorias.md",
    "Excalidraw/Lol builds.md",
    "Ingeniería Electrónica/Mecatrónica/11-Problema de las trayectorias.md",
    "Ingeniería Electrónica/Mecatrónica/Diseño de Robot.md",
    "Ingeniería Electrónica/Mecatrónica/11-Problema de las trayectorias.md",
    "Ingeniería Electrónica/Comunicaciones/Comu I/4-Modulación SSB.md",
    "Ingeniería Electrónica/Comunicaciones/Comu I/3-Modulación AM.md",
    "Ingeniería Electrónica/Mate/Matemática 6/Prepa 6 de Marquina.md.orig",
    "Mate/Matemática 6/Prepa 6 de Marquina_REMOTE_1646.md",
    "Mate/Matemática 6/Prepa 6 de Marquina_LOCAL_1646.md",
    "Mate/Matemática 6/Prepa 6 de Marquina_BASE_1646.md",
    "Mate/Matemática 6/Prepa 6 de Marquina_BACKUP_1646.md",
    "mintty.exe.stackdump",
    "conflict-files-obsidian-git.md",
    "Ingeniería Electrónica/Mecatrónica/10-Formulación de Newton-Euler.md",
    "Ingeniería Electrónica/Mate/Matemática 6",
    "Excalidraw",
    "Tags",
    "Mate 6/Guía 1.canvas",
    "Untitled 1.canvas"
  ]
}